TwitAnalysis/Tweet.py
TwitAnalysis/TwitAnalyzer.py
TwitAnalysis/TwitLive.py
TwitAnalysis/TwitProcess.py
TwitAnalysis/TwitStream.py
TwitAnalysis/__init__.py
TwitAnalysis-1.1.dist-info/LICENSE
TwitAnalysis-1.1.dist-info/METADATA
TwitAnalysis-1.1.dist-info/WHEEL
TwitAnalysis-1.1.dist-info/top_level.txt
TwitAnalysis-1.1.dist-info/RECORD
