Metadata-Version: 2.1
Name: TwitAnalysis
Version: 1.1
Summary: Package for analyzing Twitter data
Home-page: https://github.com/michaelMondoro/TwitAnalysis
Author: Michael Mondoro
Author-email: michaelmondoro@gmail.com
Classifier: Programming Language :: Python :: 3
Classifier: License :: OSI Approved :: MIT License
Classifier: Operating System :: OS Independent
Requires-Python: >=3.10
License-File: LICENSE
Requires-Dist: tweepy ==4.12.1
Requires-Dist: PyYAML
Requires-Dist: termcolor
Requires-Dist: progress
Requires-Dist: prettytable
Requires-Dist: textblob
